contribution_graph_plotter/__init__.py
contribution_graph_plotter/plotter.py
contribution_graph_plotter/soup.py
contribution_graph_plotter/templates/dark.svg
contribution_graph_plotter-0.1.0.dist-info/LICENSE
contribution_graph_plotter-0.1.0.dist-info/WHEEL
contribution_graph_plotter-0.1.0.dist-info/METADATA
contribution_graph_plotter-0.1.0.dist-info/RECORD
