Metadata-Version: 2.1
Name: contribution-graph-plotter
Version: 0.1.0
Summary: Plots anything into a GitHub contribution graph.
License: MIT
Author: Jan-Benedikt Jagusch
Author-email: jan.jagusch@gmail.com
Requires-Python: >=3.8,<4.0
Classifier: License :: OSI Approved :: MIT License
Classifier: Programming Language :: Python :: 3
Classifier: Programming Language :: Python :: 3.8
Classifier: Programming Language :: Python :: 3.9
Requires-Dist: beautifulsoup4 (>=4.9.3,<5.0.0)
Requires-Dist: numpy (>=1.20.1,<2.0.0)
